oceanepouilly_picsou/__init__.py
oceanepouilly_picsou/picsou.py
oceanepouilly_picsou-0.1.0.dist-info/METADATA
oceanepouilly_picsou-0.1.0.dist-info/WHEEL
oceanepouilly_picsou-0.1.0.dist-info/RECORD
